shohanc/__init__.py
shohanc/collections/__init__.py
shohanc/collections/ultraqueue.py
shohanc/collections/raw/ultraqueue.dll
shohanc/collections/raw/ultraqueue.so
shohanc-0.1.3.dist-info/LICENSE
shohanc-0.1.3.dist-info/METADATA
shohanc-0.1.3.dist-info/WHEEL
shohanc-0.1.3.dist-info/entry_points.txt
shohanc-0.1.3.dist-info/top_level.txt
shohanc-0.1.3.dist-info/RECORD
