Metadata-Version: 2.1
Name: shohanc
Version: 0.1.3
Summary: ⚡ Ultra-fast Python queue system with native C backend support, persistence, and encryption.
Home-page: https://github.com/shohan-dev/Shohanc-pypi-libary
Author: Shohan
Author-email: shohan.dev.cse@gmail.com
License: MIT
Keywords: queue performance c-backend encryption persistence fast scalable
Classifier: Programming Language :: Python :: 3
Classifier: License :: OSI Approved :: MIT License
Classifier: Operating System :: OS Independent
Classifier: Development Status :: 4 - Beta
Classifier: Intended Audience :: Developers
Classifier: Topic :: Software Development :: Libraries :: Python Modules
Requires-Python: >=3.7
License-File: LICENSE
Requires-Dist: cryptography>=3.0
Requires-Dist: typing-extensions; python_version < "3.8"
Provides-Extra: dev
Requires-Dist: pytest>=6.0; extra == "dev"
Requires-Dist: build; extra == "dev"
Requires-Dist: twine; extra == "dev"
